TLSFAllocator.cpython-311-darwin.so
python_example.cpython-311-darwin.so
TLSFAllocator-0.0.1.dist-info/LICENSE
TLSFAllocator-0.0.1.dist-info/METADATA
TLSFAllocator-0.0.1.dist-info/WHEEL
TLSFAllocator-0.0.1.dist-info/top_level.txt
TLSFAllocator-0.0.1.dist-info/RECORD
